[
  {
    "start": 0.0,
    "end": 5.66,
    "speaker": "彥君",
    "text": "……哈囉各位即將衝 A的會考戰士們我是彥君老師"
  },
  {
    "start": 5.66,
    "end": 11.49,
    "speaker": "彥君",
    "text": "我們的第一堂課就是來解決顯微鏡這個必考題"
  },
  {
    "start": 11.49,
    "end": 19.88,
    "speaker": "曉臻",
    "text": "準備好了這單元雖然基礎但裡面的陷阱超多大家筆記本準備好"
  },
  {
    "start": 19.88,
    "end": 23.94,
    "speaker": "曉臻",
    "text": "顯微鏡最常考的第一點就是倍率"
  },
  {
    "start": 23.94,
    "end": 27.94,
    "speaker": "曉臻",
    "text": "學生常混淆長短跟倍率的關係"
  },
  {
    "start": 27.94,
    "end": 31.94,
    "speaker": "彥君",
    "text": "目短物長倍率高"
  },
  {
    "start": 31.94,
    "end": 39.76,
    "speaker": "彥君",
    "text": "目鏡靠近眼睛越短倍率越高物鏡靠近標本越長倍率越高"
  },
  {
    "start": 39.76,
    "end": 44.3,
    "speaker": "曉臻",
    "text": "老師為什麼物鏡是越長倍率越高啊"
  },
  {
    "start": 44.3,
    "end": 50.82,
    "speaker": "彥君",
    "text": "因為物鏡越長代表裡面的透鏡組越複雜可以把影像放得更大"
  },
  {
    "start": 50.82,
    "end": 56.38,
    "speaker": "彥君",
    "text": "所以考題如果給你一組鏡頭組合要選倍率最高的"
  },
  {
    "start": 56.38,
    "end": 60.96,
    "speaker": "彥君",
    "text": "就挑最短的目鏡配上最長的物鏡"
  },
  {
    "start": 60.96,
    "end": 67.08,
    "speaker": "曉臻",
    "text": "大家想像一下長長的物鏡快要撞到玻片那個就是高倍"
  },
  {
    "start": 67.08,
    "end": 69.98,
    "speaker": "曉臻",
    "text": "那總倍率怎麼計算"
  },
  {
    "start": 69.98,
    "end": 76.02,
    "speaker": "彥君",
    "text": "相乘就對了這時候視野會發生四個變化"
  },
  {
    "start": 76.02,
    "end": 80.46,
    "speaker": "彥君",
    "text": "第一亮度變暗進光量變少"
  },
  {
    "start": 80.46,
    "end": 85.69,
    "speaker": "彥君",
    "text": "第二範圍變小看到的細胞數量也變少"
  },
  {
    "start": 85.69,
    "end": 91.61,
    "speaker": "彥君",
    "text": "第三細節變大細胞看起來變清晰變大了"
  },
  {
    "start": 91.61,
    "end": 97.03,
    "speaker": "彥君",
    "text": "第四焦距變短物鏡會非常靠近玻片"
  },
  {
    "start": 97.03,
    "end": 102.16,
    "speaker": "曉臻",
    "text": "倍率高就是看得很清楚但視野變窄變暗"
  },
  {
    "start": 102.16,
    "end": 107.1,
    "speaker": "曉臻",
    "text": "倍率越高除了細節其他都變少變暗"
  },
  {
    "start": 107.1,
    "end": 112.04,
    "speaker": "曉臻",
    "text": "老師複式顯微鏡的成像最容易轉不過來"
  },
  {
    "start": 112.04,
    "end": 118.62,
    "speaker": "彥君",
    "text": "沒錯複式顯微鏡是上下顛倒左右相反"
  },
  {
    "start": 118.62,
    "end": 124.92,
    "speaker": "彥君",
    "text": "紙上寫小寫的 pq目鏡看起來就是小寫的 bd"
  },
  {
    "start": 124.92,
    "end": 128.54,
    "speaker": "曉臻",
    "text": "老師如果是大寫的 Ｐ 呢"
  },
  {
    "start": 128.54,
    "end": 134.61,
    "speaker": "彥君",
    "text": "如果是大寫的 Ｐ轉一百八十度看起來就會像小寫的 ｄ"
  },
  {
    "start": 134.61,
    "end": 140.73,
    "speaker": "彥君",
    "text": "最簡單的方法就是直接把考卷旋轉一百八十度就是答案"
  },
  {
    "start": 140.73,
    "end": 145.33,
    "speaker": "曉臻",
    "text": "那移動法則呢這一定要背下來"
  },
  {
    "start": 145.33,
    "end": 149.1,
    "speaker": "彥君",
    "text": "物在哪裡就往哪裡移"
  },
  {
    "start": 149.1,
    "end": 154.2,
    "speaker": "彥君",
    "text": "目標在左下方你就把玻片往左下方移"
  },
  {
    "start": 154.2,
    "end": 159.31,
    "speaker": "彥君",
    "text": "目標在右上方你就把玻片往右上方移"
  },
  {
    "start": 159.31,
    "end": 162.86,
    "speaker": "曉臻",
    "text": "為什麼要往一樣的方向移啊"
  },
  {
    "start": 162.86,
    "end": 170.75,
    "speaker": "彥君",
    "text": "因為顯微鏡裡面是反的你往左下移影像其實是往右上跑這樣才會回到中間"
  },
  {
    "start": 170.75,
    "end": 178.16,
    "speaker": "曉臻",
    "text": "喔所以戰士們看到生物在右上你就追著它往右上移就對了"
  },
  {
    "start": 178.16,
    "end": 181.5,
    "speaker": "曉臻",
    "text": "那如果是解剖顯微鏡呢"
  },
  {
    "start": 181.5,
    "end": 187.47,
    "speaker": "彥君",
    "text": "解剖顯微鏡沒有顛倒所見即所得"
  },
  {
    "start": 187.47,
    "end": 193.15,
    "speaker": "彥君",
    "text": "這通常用來看比較大不透光不需要切片的物體"
  },
  {
    "start": 193.15,
    "end": 198.09,
    "speaker": "曉臻",
    "text": "老師由低倍換到高倍一定要照順序嗎"
  },
  {
    "start": 198.09,
    "end": 202.74,
    "speaker": "彥君",
    "text": "當然這是保命符"
  },
  {
    "start": 202.74,
    "end": 209.27,
    "speaker": "彥君",
    "text": "第一步先置中在低倍下一定要先把目標移到正中間"
  },
  {
    "start": 209.27,
    "end": 216.3,
    "speaker": "曉臻",
    "text": "這步超重要如果不先置中一換高倍目標會直接消失"
  },
  {
    "start": 216.3,
    "end": 221.93,
    "speaker": "彥君",
    "text": "第二步換物鏡直接轉動旋轉盤"
  },
  {
    "start": 221.93,
    "end": 229.49,
    "speaker": "彥君",
    "text": "第三步調亮度換到高倍會變暗要調大光圈或用凹面鏡"
  },
  {
    "start": 229.49,
    "end": 234.04,
    "speaker": "曉臻",
    "text": "大家記住高倍就是要大光圈配凹面鏡"
  },
  {
    "start": 234.04,
    "end": 237.3,
    "speaker": "彥君",
    "text": "最後一步調焦距"
  },
  {
    "start": 237.3,
    "end": 243.13,
    "speaker": "彥君",
    "text": "嚴禁動粗調節輪只能動細調節輪"
  },
  {
    "start": 243.13,
    "end": 246.8,
    "speaker": "曉臻",
    "text": "為什麼高倍不能動粗調節輪"
  },
  {
    "start": 246.8,
    "end": 253.92,
    "speaker": "彥君",
    "text": "因為高倍物鏡很長動粗調節輪會直接壓碎玻片甚至撞壞鏡頭"
  },
  {
    "start": 253.92,
    "end": 257.38,
    "speaker": "彥君",
    "text": "最後複習今天的核心"
  },
  {
    "start": 257.38,
    "end": 261.14,
    "speaker": "彥君",
    "text": "鏡頭目短物長倍率最強"
  },
  {
    "start": 261.14,
    "end": 265.24,
    "speaker": "彥君",
    "text": "成像複式全反解剖鏡相同"
  },
  {
    "start": 265.24,
    "end": 268.98,
    "speaker": "彥君",
    "text": "位移物在哪就往哪移"
  },
  {
    "start": 268.98,
    "end": 274.78,
    "speaker": "彥君",
    "text": "高倍先置中後換鏡只能動細調節輪"
  },
  {
    "start": 274.78,
    "end": 278.31,
    "speaker": "曉臻",
    "text": "戰士們放下手機喝口水"
  },
  {
    "start": 278.31,
    "end": 282.7,
    "speaker": "曉臻",
    "text": "閉上眼在腦海裡操作一次顯微鏡"
  },
  {
    "start": 282.7,
    "end": 285.6,
    "speaker": "彥君",
    "text": "我是彥君老師"
  },
  {
    "start": 285.6,
    "end": 288.23,
    "speaker": "曉臻",
    "text": "我是曉臻助教"
  },
  {
    "start": 288.23,
    "end": 290.89,
    "speaker": "曉臻",
    "text": "我們下個單元見"
  }
]