[
  {
    "start": 0.0,
    "end": 3.98,
    "speaker": "彥君",
    "text": "戰士們 我們繼續往下看"
  },
  {
    "start": 3.98,
    "end": 8.92,
    "speaker": "曉臻",
    "text": "接下來這張板塊運動的圖 也是必考重點喔"
  },
  {
    "start": 8.92,
    "end": 14.77,
    "speaker": "彥君",
    "text": "沒錯 剛剛說過軟流圈 就像濃稠的熱巧克力"
  },
  {
    "start": 14.77,
    "end": 19.57,
    "speaker": "曉臻",
    "text": "投影片上有寫 軟流圈會發生『熱對流』"
  },
  {
    "start": 19.57,
    "end": 24.41,
    "speaker": "彥君",
    "text": "對 這就是帶動板塊移動的巨大引擎"
  },
  {
    "start": 24.41,
    "end": 29.69,
    "speaker": "彥君",
    "text": "考試最愛考兩種板塊交界 第一種是拉開的"
  },
  {
    "start": 29.69,
    "end": 34.53,
    "speaker": "曉臻",
    "text": "就像把披薩從中間拉開 會牽絲一樣嗎？"
  },
  {
    "start": 34.53,
    "end": 39.52,
    "speaker": "彥君",
    "text": "這個比喻很好 這叫做『張裂性』板塊交界"
  },
  {
    "start": 39.52,
    "end": 44.7,
    "speaker": "曉臻",
    "text": "披薩底下的熱起司冒出來 就像岩漿湧出對吧"
  },
  {
    "start": 44.7,
    "end": 50.29,
    "speaker": "彥君",
    "text": "完全正確 岩漿冷卻後 就會變成新的地殼"
  },
  {
    "start": 50.29,
    "end": 54.92,
    "speaker": "曉臻",
    "text": "如果在海底被拉開 會變成什麼地形啊？"
  },
  {
    "start": 54.92,
    "end": 60.07,
    "speaker": "彥君",
    "text": "會形成海底的火山山脈 叫做『中洋脊』"
  },
  {
    "start": 60.07,
    "end": 65.08,
    "speaker": "曉臻",
    "text": "老師 那世界上有什麼必考的張裂性例子嗎？"
  },
  {
    "start": 65.08,
    "end": 69.23,
    "speaker": "彥君",
    "text": "第一個必考點 就是『冰島』"
  },
  {
    "start": 69.23,
    "end": 74.51,
    "speaker": "曉臻",
    "text": "冰島剛好在中洋脊上 正在被慢慢拉成兩半喔"
  },
  {
    "start": 74.51,
    "end": 79.71,
    "speaker": "彥君",
    "text": "沒錯 還有第二個例子 發生在陸地上"
  },
  {
    "start": 79.71,
    "end": 82.66,
    "speaker": "曉臻",
    "text": "陸地也會被拉開嗎？"
  },
  {
    "start": 82.66,
    "end": 87.34,
    "speaker": "彥君",
    "text": "會的 像是著名的『東非大裂谷』"
  },
  {
    "start": 87.34,
    "end": 92.68,
    "speaker": "曉臻",
    "text": "哇 那邊的大地正在裂開 以後會變成海洋嗎？"
  },
  {
    "start": 92.68,
    "end": 97.94,
    "speaker": "彥君",
    "text": "很有可能喔這就是張裂性的威力"
  },
  {
    "start": 97.94,
    "end": 102.47,
    "speaker": "彥君",
    "text": "那第二種交界 如果兩個板塊對撞呢？"
  },
  {
    "start": 102.47,
    "end": 107.67,
    "speaker": "曉臻",
    "text": "碰的一聲這叫做『聚合性』板塊交界"
  },
  {
    "start": 107.67,
    "end": 113.64,
    "speaker": "彥君",
    "text": "沒錯 就像兩台車對撞 引擎蓋會擠壓凸起來"
  },
  {
    "start": 113.64,
    "end": 118.22,
    "speaker": "曉臻",
    "text": "岩石被擠壓凸起 就會變成高山對吧？"
  },
  {
    "start": 118.22,
    "end": 123.93,
    "speaker": "彥君",
    "text": "對 這叫做『造山運動』 台灣就是最好的例子"
  },
  {
    "start": 123.93,
    "end": 129.18,
    "speaker": "曉臻",
    "text": "歐亞板塊跟菲律賓海板塊 就在我們這裡相撞"
  },
  {
    "start": 129.18,
    "end": 134.2,
    "speaker": "彥君",
    "text": "所以台灣才有這麼多高山 像是中央山脈"
  },
  {
    "start": 134.2,
    "end": 139.26,
    "speaker": "曉臻",
    "text": "老師 那世界上還有其他聚合性的例子嗎？"
  },
  {
    "start": 139.26,
    "end": 145.35,
    "speaker": "彥君",
    "text": "當然有全世界最高的『喜馬拉雅山』"
  },
  {
    "start": 145.35,
    "end": 148.92,
    "speaker": "曉臻",
    "text": "這是哪兩個板塊撞出來的啊？"
  },
  {
    "start": 148.92,
    "end": 153.55,
    "speaker": "彥君",
    "text": "是歐亞板塊 迎面撞上印澳板塊"
  },
  {
    "start": 153.55,
    "end": 158.68,
    "speaker": "曉臻",
    "text": "難怪山會這麼高 原來是陸地跟陸地的大車禍"
  },
  {
    "start": 158.68,
    "end": 164.32,
    "speaker": "彥君",
    "text": "形容得很好 但如果是海洋撞上陸地呢？"
  },
  {
    "start": 164.32,
    "end": 168.75,
    "speaker": "曉臻",
    "text": "海洋板塊比較重 應該會往下鑽吧？"
  },
  {
    "start": 168.75,
    "end": 174.29,
    "speaker": "彥君",
    "text": "沒錯 往下鑽的深溝 就會形成『海溝』"
  },
  {
    "start": 174.29,
    "end": 178.54,
    "speaker": "曉臻",
    "text": "像是世界上最深的『馬里亞納海溝』"
  },
  {
    "start": 178.54,
    "end": 185.18,
    "speaker": "彥君",
    "text": "答對了 而且板塊往下鑽的時候 會摩擦生熱"
  },
  {
    "start": 185.18,
    "end": 189.59,
    "speaker": "曉臻",
    "text": "岩漿往上噴發 就會形成火山了嗎？"
  },
  {
    "start": 189.59,
    "end": 193.79,
    "speaker": "彥君",
    "text": "對 這就是『火山島弧』的由來"
  },
  {
    "start": 193.79,
    "end": 198.39,
    "speaker": "曉臻",
    "text": "老師 那日本是不是就是這樣形成的？"
  },
  {
    "start": 198.39,
    "end": 203.52,
    "speaker": "彥君",
    "text": "完全正確 包含太平洋周圍的火環帶都是"
  },
  {
    "start": 203.52,
    "end": 208.25,
    "speaker": "曉臻",
    "text": "原來聚合性交界 不只會有高山跟海溝"
  },
  {
    "start": 208.25,
    "end": 212.49,
    "speaker": "曉臻",
    "text": "還會伴隨著大量的地震跟火山活動"
  },
  {
    "start": 212.49,
    "end": 217.91,
    "speaker": "彥君",
    "text": "戰士們 張裂跟聚合的例子 絕對要分清楚"
  },
  {
    "start": 217.91,
    "end": 222.35,
    "speaker": "彥君",
    "text": "這個段落的重點 我們先整理到這邊"
  },
  {
    "start": 222.35,
    "end": 226.95,
    "speaker": "曉臻",
    "text": "大家把圖表的例子看熟 我們等等繼續"
  }
]