[
  {
    "start": 0.0,
    "end": 4.98,
    "speaker": "彥君",
    "text": "戰士們 堅持到最後就是贏家",
    "is_pinned": false,
    "pin_level": 0,
    "commands": []
  },
  {
    "start": 5.18,
    "end": 8.95,
    "speaker": "彥君",
    "text": "每一滴汗水都在為夢想鋪路",
    "is_pinned": false,
    "pin_level": 0,
    "commands": []
  },
  {
    "start": 9.15,
    "end": 12.71,
    "speaker": "彥君",
    "text": "各位衝刺 $A^{++}$ 級的戰士們",
    "is_pinned": false,
    "pin_level": 0,
    "commands": [
      "$A^{++}$"
    ]
  },
  {
    "start": 12.91,
    "end": 16.38,
    "speaker": "彥君",
    "text": "恭喜大家來到第七十三集囉",
    "is_pinned": false,
    "pin_level": 0,
    "commands": []
  },
  {
    "start": 16.58,
    "end": 20.09,
    "speaker": "彥君",
    "text": "戰士們好 我是彥君老師",
    "is_pinned": false,
    "pin_level": 0,
    "commands": []
  },
  {
    "start": 20.29,
    "end": 23.58,
    "speaker": "曉臻",
    "text": "大家好啊 我是曉臻助教",
    "is_pinned": false,
    "pin_level": 0,
    "commands": []
  },
  {
    "start": 23.78,
    "end": 27.27,
    "speaker": "曉臻",
    "text": "老師今天要講兩顆星大魔王",
    "is_pinned": false,
    "pin_level": 0,
    "commands": []
  },
  {
    "start": 27.47,
    "end": 30.89,
    "speaker": "曉臻",
    "text": "也就是理化必考的回聲觀念",
    "is_pinned": false,
    "pin_level": 0,
    "commands": []
  },
  {
    "start": 31.09,
    "end": 35.99,
    "speaker": "彥君",
    "text": "沒錯 戰士們請務必要記住",
    "is_pinned": false,
    "pin_level": 0,
    "commands": []
  },
  {
    "start": 36.19,
    "end": 39.78,
    "speaker": "彥君",
    "text": "回聲跟原本發出去的聲音啊",
    "is_pinned": false,
    "pin_level": 0,
    "commands": []
  },
  {
    "start": 39.98,
    "end": 43.73,
    "speaker": "彥君",
    "text": "只有振幅跟方向是不一樣的",
    "is_pinned": false,
    "pin_level": 0,
    "commands": []
  },
  {
    "start": 43.93,
    "end": 47.7,
    "speaker": "彥君",
    "text": "其他的條件通通都不會改變",
    "is_pinned": false,
    "pin_level": 0,
    "commands": []
  },
  {
    "start": 47.9,
    "end": 160.77,
    "speaker": "彥君",
    "text": "① 回聲與原聲僅振幅與方向不同",
    "is_pinned": true,
    "pin_level": 1,
    "commands": [
      "釘選",
      "① 回聲與原聲僅振幅(服)與方向不同"
    ]
  },
  {
    "start": 52.48,
    "end": 56.09,
    "speaker": "曉臻",
    "text": "老師講義上說至少十七公尺",
    "is_pinned": false,
    "pin_level": 0,
    "commands": []
  },
  {
    "start": 56.29,
    "end": 59.61,
    "speaker": "曉臻",
    "text": "才聽得到自己的回聲出現耶",
    "is_pinned": false,
    "pin_level": 0,
    "commands": []
  },
  {
    "start": 59.81,
    "end": 63.1,
    "speaker": "曉臻",
    "text": "這個十七公尺怎麼算出來的",
    "is_pinned": false,
    "pin_level": 0,
    "commands": []
  },
  {
    "start": 63.3,
    "end": 67.06,
    "speaker": "彥君",
    "text": "戰士們仔細聽好這經典計算",
    "is_pinned": false,
    "pin_level": 0,
    "commands": []
  },
  {
    "start": 67.26,
    "end": 70.82,
    "speaker": "彥君",
    "text": "人類耳朵要分辨出回聲的話",
    "is_pinned": false,
    "pin_level": 0,
    "commands": []
  },
  {
    "start": 71.02,
    "end": 74.55,
    "speaker": "彥君",
    "text": "中間至少需要零點一秒時間",
    "is_pinned": false,
    "pin_level": 0,
    "commands": []
  },
  {
    "start": 74.75,
    "end": 78.48,
    "speaker": "彥君",
    "text": "聲音秒速三百四十乘零點一",
    "is_pinned": false,
    "pin_level": 0,
    "commands": []
  },
  {
    "start": 78.68,
    "end": 82.38,
    "speaker": "彥君",
    "text": "代表聲音來回走三十四公尺",
    "is_pinned": false,
    "pin_level": 0,
    "commands": []
  },
  {
    "start": 82.58,
    "end": 86.17,
    "speaker": "彥君",
    "text": "再除以二單趟就是十七公尺",
    "is_pinned": false,
    "pin_level": 0,
    "commands": []
  },
  {
    "start": 86.37,
    "end": 160.77,
    "speaker": "彥君",
    "text": "② $\\text{單趟} = \\frac{340\\text{m/s} \\times 0.1\\text{s}}{2} = 17\\text{m}$",
    "is_pinned": true,
    "pin_level": 2,
    "commands": [
      "釘選",
      "② $\\text{單趟} = \\frac{340\\text{m/s} \\times 0.1\\text{s}}{2} = 17\\text{m}$"
    ]
  },
  {
    "start": 90.34,
    "end": 94.74,
    "speaker": "曉臻",
    "text": "哇 來回除以二推導太清楚了",
    "is_pinned": false,
    "pin_level": 0,
    "commands": []
  },
  {
    "start": 94.94,
    "end": 98.74,
    "speaker": "彥君",
    "text": "接下來看超聲波的必考重點",
    "is_pinned": false,
    "pin_level": 0,
    "commands": []
  },
  {
    "start": 98.94,
    "end": 102.36,
    "speaker": "彥君",
    "text": "它的頻率超過了兩萬赫茲喔",
    "is_pinned": false,
    "pin_level": 0,
    "commands": []
  },
  {
    "start": 102.56,
    "end": 105.88,
    "speaker": "彥君",
    "text": "因為這種聲音人類聽不到啊",
    "is_pinned": false,
    "pin_level": 0,
    "commands": []
  },
  {
    "start": 106.08,
    "end": 109.45,
    "speaker": "彥君",
    "text": "所以它有很多的神奇應用喔",
    "is_pinned": false,
    "pin_level": 0,
    "commands": []
  },
  {
    "start": 109.65,
    "end": 160.77,
    "speaker": "彥君",
    "text": "③ 超聲波頻率超過兩萬赫茲",
    "is_pinned": true,
    "pin_level": 3,
    "commands": [
      "釘選",
      "③ 超聲波頻率超過兩萬赫茲(茲)"
    ]
  },
  {
    "start": 113.82,
    "end": 117.3,
    "speaker": "曉臻",
    "text": "像是漁船判斷海底的水深啊",
    "is_pinned": false,
    "pin_level": 0,
    "commands": []
  },
  {
    "start": 117.5,
    "end": 120.92,
    "speaker": "曉臻",
    "text": "倒車雷達還有超音波的掃描",
    "is_pinned": false,
    "pin_level": 0,
    "commands": []
  },
  {
    "start": 121.12,
    "end": 126.12,
    "speaker": "彥君",
    "text": "沒錯 還有蝙蝠晚上的飛行",
    "is_pinned": false,
    "pin_level": 0,
    "commands": []
  },
  {
    "start": 126.32,
    "end": 129.86,
    "speaker": "彥君",
    "text": "跟洗眼鏡的超音波清潔機喔",
    "is_pinned": false,
    "pin_level": 0,
    "commands": []
  },
  {
    "start": 130.06,
    "end": 133.47,
    "speaker": "曉臻",
    "text": "老師那如果想要避免掉回聲",
    "is_pinned": false,
    "pin_level": 0,
    "commands": []
  },
  {
    "start": 133.67,
    "end": 137.09,
    "speaker": "曉臻",
    "text": "怕被回聲干擾到底該怎麼辦",
    "is_pinned": false,
    "pin_level": 0,
    "commands": []
  },
  {
    "start": 137.29,
    "end": 142.24,
    "speaker": "彥君",
    "text": "很簡單 只要使用柔軟材質",
    "is_pinned": false,
    "pin_level": 0,
    "commands": []
  },
  {
    "start": 142.44,
    "end": 145.95,
    "speaker": "彥君",
    "text": "或者是表面不平整的牆壁啊",
    "is_pinned": false,
    "pin_level": 0,
    "commands": []
  },
  {
    "start": 146.15,
    "end": 149.86,
    "speaker": "彥君",
    "text": "就能夠把聲音吸收或打散掉",
    "is_pinned": false,
    "pin_level": 0,
    "commands": []
  },
  {
    "start": 150.06,
    "end": 153.5,
    "speaker": "彥君",
    "text": "這樣就能完美避免掉回聲囉",
    "is_pinned": false,
    "pin_level": 0,
    "commands": []
  },
  {
    "start": 153.7,
    "end": 160.77,
    "speaker": "彥君",
    "text": "④ 柔軟不平整材質可避免回聲",
    "is_pinned": true,
    "pin_level": 4,
    "commands": [
      "釘選",
      "④ 柔軟不平整材質可避免回聲"
    ]
  },
  {
    "start": 160.77,
    "end": 164.81,
    "speaker": "曉臻",
    "text": "我懂了 柔軟不平整的材質",
    "is_pinned": false,
    "pin_level": 0,
    "commands": []
  },
  {
    "start": 165.01,
    "end": 168.3,
    "speaker": "曉臻",
    "text": "就能夠完美地消滅掉回聲啦",
    "is_pinned": false,
    "pin_level": 0,
    "commands": []
  },
  {
    "start": 168.5,
    "end": 172.4,
    "speaker": "彥君",
    "text": "觀念全通了秒殺考題沒問題",
    "is_pinned": false,
    "pin_level": 0,
    "commands": []
  },
  {
    "start": 172.6,
    "end": 175.87,
    "speaker": "彥君",
    "text": "帶著這份底氣迎戰會考吧",
    "is_pinned": false,
    "pin_level": 0,
    "commands": []
  },
  {
    "start": 176.07,
    "end": 179.56,
    "speaker": "彥君",
    "text": "戰士們 我是彥君老師",
    "is_pinned": false,
    "pin_level": 0,
    "commands": []
  },
  {
    "start": 179.76,
    "end": 183.06,
    "speaker": "曉臻",
    "text": "大家好啊 我是曉臻助教",
    "is_pinned": false,
    "pin_level": 0,
    "commands": []
  },
  {
    "start": 183.26,
    "end": 186.38,
    "speaker": "合聲",
    "text": "來回除二 柔軟吸音",
    "is_pinned": false,
    "pin_level": 0,
    "commands": []
  },
  {
    "start": 186.58,
    "end": 190.12,
    "speaker": "合聲",
    "text": "戰士們 我們頂峰相見",
    "is_pinned": false,
    "pin_level": 0,
    "commands": []
  }
]