[
  {
    "start": 0.0,
    "end": 4.64,
    "speaker": "彥君",
    "text": "各位拚盡全力、絕不放棄的會考戰士們",
    "is_pinned": false,
    "pin_level": 0,
    "commands": []
  },
  {
    "start": 4.84,
    "end": 7.44,
    "speaker": "彥君",
    "text": "我是彥君老師",
    "is_pinned": false,
    "pin_level": 0,
    "commands": []
  },
  {
    "start": 7.64,
    "end": 9.93,
    "speaker": "曉臻",
    "text": "戰士們大家好",
    "is_pinned": false,
    "pin_level": 0,
    "commands": []
  },
  {
    "start": 10.13,
    "end": 12.46,
    "speaker": "曉臻",
    "text": "我是曉臻助教",
    "is_pinned": false,
    "pin_level": 0,
    "commands": []
  },
  {
    "start": 12.66,
    "end": 15.98,
    "speaker": "彥君",
    "text": "歡迎來到第九十六集",
    "is_pinned": false,
    "pin_level": 0,
    "commands": []
  },
  {
    "start": 16.18,
    "end": 20.42,
    "speaker": "彥君",
    "text": "戰士們注意有機化學內容非常多",
    "is_pinned": false,
    "pin_level": 0,
    "commands": []
  },
  {
    "start": 20.62,
    "end": 23.79,
    "speaker": "彥君",
    "text": "這可是會考的超級熱區",
    "is_pinned": false,
    "pin_level": 0,
    "commands": []
  },
  {
    "start": 23.99,
    "end": 26.76,
    "speaker": "曉臻",
    "text": "老師講義第一行",
    "is_pinned": false,
    "pin_level": 0,
    "commands": []
  },
  {
    "start": 26.96,
    "end": 29.37,
    "speaker": "曉臻",
    "text": "寫著生命物質",
    "is_pinned": false,
    "pin_level": 0,
    "commands": []
  },
  {
    "start": 29.57,
    "end": 32.46,
    "speaker": "彥君",
    "text": "早期科學家認為",
    "is_pinned": false,
    "pin_level": 0,
    "commands": []
  },
  {
    "start": 32.66,
    "end": 36.36,
    "speaker": "彥君",
    "text": "只有生命體才能製造有機物",
    "is_pinned": false,
    "pin_level": 0,
    "commands": []
  },
  {
    "start": 36.56,
    "end": 39.35,
    "speaker": "曉臻",
    "text": "那後來怎麼被推翻了",
    "is_pinned": false,
    "pin_level": 0,
    "commands": []
  },
  {
    "start": 39.55,
    "end": 42.99,
    "speaker": "彥君",
    "text": "後來有位科學家叫做烏拉",
    "is_pinned": false,
    "pin_level": 0,
    "commands": []
  },
  {
    "start": 43.19,
    "end": 46.01,
    "speaker": "彥君",
    "text": "他在實驗室裡面",
    "is_pinned": false,
    "pin_level": 0,
    "commands": []
  },
  {
    "start": 46.21,
    "end": 49.36,
    "speaker": "彥君",
    "text": "意外人工合成了尿素",
    "is_pinned": false,
    "pin_level": 0,
    "commands": []
  },
  {
    "start": 49.56,
    "end": 53.05,
    "speaker": "曉臻",
    "text": "哇尿素是有機物",
    "is_pinned": false,
    "pin_level": 0,
    "commands": []
  },
  {
    "start": 53.25,
    "end": 56.38,
    "speaker": "曉臻",
    "text": "竟然用人工合成出來了",
    "is_pinned": false,
    "pin_level": 0,
    "commands": []
  },
  {
    "start": 56.58,
    "end": 61.38,
    "speaker": "彥君",
    "text": "沒錯所以有機物的定義改了",
    "is_pinned": false,
    "pin_level": 0,
    "commands": []
  },
  {
    "start": 61.58,
    "end": 64.52,
    "speaker": "彥君",
    "text": "現在的有機化合物",
    "is_pinned": false,
    "pin_level": 0,
    "commands": []
  },
  {
    "start": 64.72,
    "end": 67.63,
    "speaker": "彥君",
    "text": "就是含碳的化合物",
    "is_pinned": false,
    "pin_level": 0,
    "commands": []
  },
  {
    "start": 67.83,
    "end": 71.44,
    "speaker": "曉臻",
    "text": "所以只要有碳就是有機物嗎",
    "is_pinned": false,
    "pin_level": 0,
    "commands": []
  },
  {
    "start": 71.64,
    "end": 74.96,
    "speaker": "彥君",
    "text": "戰士們大陷阱來了",
    "is_pinned": false,
    "pin_level": 0,
    "commands": []
  },
  {
    "start": 75.16,
    "end": 78.07,
    "speaker": "彥君",
    "text": "有幾個叛徒是例外",
    "is_pinned": false,
    "pin_level": 0,
    "commands": []
  },
  {
    "start": 78.27,
    "end": 82.05,
    "speaker": "彥君",
    "text": "像是一氧化碳、二氧化碳",
    "is_pinned": false,
    "pin_level": 0,
    "commands": []
  },
  {
    "start": 82.25,
    "end": 85.18,
    "speaker": "曉臻",
    "text": "還有碳酸鹽類對不對",
    "is_pinned": false,
    "pin_level": 0,
    "commands": []
  },
  {
    "start": 85.38,
    "end": 90.46,
    "speaker": "彥君",
    "text": "沒錯這些雖然含有碳元素",
    "is_pinned": false,
    "pin_level": 0,
    "commands": []
  },
  {
    "start": 90.66,
    "end": 93.62,
    "speaker": "彥君",
    "text": "但它們卻是無機物喔",
    "is_pinned": false,
    "pin_level": 0,
    "commands": []
  },
  {
    "start": 93.82,
    "end": 108.58,
    "speaker": "彥君",
    "text": "有機必含碳，含碳不一定是有機物",
    "is_pinned": true,
    "pin_level": 1,
    "commands": [
      "釘選"
    ]
  },
  {
    "start": 101.08,
    "end": 105.38,
    "speaker": "彥君",
    "text": "給你們三秒鐘把這句話刻在腦海裡",
    "is_pinned": false,
    "pin_level": 0,
    "commands": []
  },
  {
    "start": 108.58,
    "end": 111.88,
    "speaker": "曉臻",
    "text": "老師接著看木材乾餾",
    "is_pinned": false,
    "pin_level": 0,
    "commands": []
  },
  {
    "start": 112.08,
    "end": 115.11,
    "speaker": "曉臻",
    "text": "為什麼要隔絕空氣加熱啊",
    "is_pinned": false,
    "pin_level": 0,
    "commands": []
  },
  {
    "start": 115.31,
    "end": 118.39,
    "speaker": "彥君",
    "text": "如果你直接拿木材去燒",
    "is_pinned": false,
    "pin_level": 0,
    "commands": []
  },
  {
    "start": 118.59,
    "end": 121.6,
    "speaker": "彥君",
    "text": "它就直接變成灰燼了",
    "is_pinned": false,
    "pin_level": 0,
    "commands": []
  },
  {
    "start": 121.8,
    "end": 125.05,
    "speaker": "彥君",
    "text": "隔絕空氣才能把它悶烤",
    "is_pinned": false,
    "pin_level": 0,
    "commands": []
  },
  {
    "start": 125.25,
    "end": 128.45,
    "speaker": "彥君",
    "text": "逼出裡面真正的成分",
    "is_pinned": false,
    "pin_level": 0,
    "commands": []
  },
  {
    "start": 128.65,
    "end": 132.62,
    "speaker": "曉臻",
    "text": "喔所以這是化學變化嗎",
    "is_pinned": false,
    "pin_level": 0,
    "commands": []
  },
  {
    "start": 132.82,
    "end": 137.46,
    "speaker": "彥君",
    "text": "沒錯因為產生了新物質",
    "is_pinned": false,
    "pin_level": 0,
    "commands": []
  },
  {
    "start": 137.66,
    "end": 141.26,
    "speaker": "彥君",
    "text": "像是焦油還有可燃性氣體",
    "is_pinned": false,
    "pin_level": 0,
    "commands": []
  },
  {
    "start": 141.46,
    "end": 144.78,
    "speaker": "彥君",
    "text": "最後剩下的黑色固體",
    "is_pinned": false,
    "pin_level": 0,
    "commands": []
  },
  {
    "start": 144.98,
    "end": 148.02,
    "speaker": "彥君",
    "text": "就能檢驗出碳元素",
    "is_pinned": false,
    "pin_level": 0,
    "commands": []
  },
  {
    "start": 148.22,
    "end": 217.49,
    "speaker": "彥君",
    "text": "木材乾餾：化學變化",
    "is_pinned": true,
    "pin_level": 1,
    "commands": [
      "釘選"
    ]
  },
  {
    "start": 153.56,
    "end": 155.8,
    "speaker": "曉臻",
    "text": "那石油分餾呢",
    "is_pinned": false,
    "pin_level": 0,
    "commands": []
  },
  {
    "start": 156.0,
    "end": 158.65,
    "speaker": "曉臻",
    "text": "它也是加熱分離耶",
    "is_pinned": false,
    "pin_level": 0,
    "commands": []
  },
  {
    "start": 158.85,
    "end": 162.29,
    "speaker": "彥君",
    "text": "戰士們這裡絕對必考",
    "is_pinned": false,
    "pin_level": 0,
    "commands": []
  },
  {
    "start": 162.49,
    "end": 166.17,
    "speaker": "彥君",
    "text": "石油分餾是純粹的物理變化",
    "is_pinned": false,
    "pin_level": 0,
    "commands": []
  },
  {
    "start": 166.37,
    "end": 170.07,
    "speaker": "曉臻",
    "text": "咦為什麼是物理變化",
    "is_pinned": false,
    "pin_level": 0,
    "commands": []
  },
  {
    "start": 170.27,
    "end": 173.95,
    "speaker": "彥君",
    "text": "因為它是利用沸點不同來分離",
    "is_pinned": false,
    "pin_level": 0,
    "commands": []
  },
  {
    "start": 174.15,
    "end": 177.66,
    "speaker": "彥君",
    "text": "沸點低的變成氣體往上跑",
    "is_pinned": false,
    "pin_level": 0,
    "commands": []
  },
  {
    "start": 177.86,
    "end": 180.8,
    "speaker": "彥君",
    "text": "像是瓦斯跟汽油",
    "is_pinned": false,
    "pin_level": 0,
    "commands": []
  },
  {
    "start": 181.0,
    "end": 184.32,
    "speaker": "彥君",
    "text": "沸點高的就會留在底下",
    "is_pinned": false,
    "pin_level": 0,
    "commands": []
  },
  {
    "start": 184.52,
    "end": 187.46,
    "speaker": "彥君",
    "text": "像是鋪馬路的瀝青",
    "is_pinned": false,
    "pin_level": 0,
    "commands": []
  },
  {
    "start": 187.66,
    "end": 191.58,
    "speaker": "曉臻",
    "text": "喔只是把它們分開而已",
    "is_pinned": false,
    "pin_level": 0,
    "commands": []
  },
  {
    "start": 191.78,
    "end": 194.66,
    "speaker": "曉臻",
    "text": "完全沒有產生新物質",
    "is_pinned": false,
    "pin_level": 0,
    "commands": []
  },
  {
    "start": 194.86,
    "end": 199.38,
    "speaker": "彥君",
    "text": "對而且分出來的產物",
    "is_pinned": false,
    "pin_level": 0,
    "commands": []
  },
  {
    "start": 199.58,
    "end": 202.42,
    "speaker": "彥君",
    "text": "依然都是混合物喔",
    "is_pinned": false,
    "pin_level": 0,
    "commands": []
  },
  {
    "start": 202.62,
    "end": 217.49,
    "speaker": "彥君",
    "text": "石油分餾：物理變化、混合物",
    "is_pinned": true,
    "pin_level": 2,
    "commands": [
      "釘選"
    ]
  },
  {
    "start": 210.06,
    "end": 214.29,
    "speaker": "彥君",
    "text": "給你們三秒鐘這兩個絕對不能搞混",
    "is_pinned": false,
    "pin_level": 0,
    "commands": []
  },
  {
    "start": 217.49,
    "end": 220.98,
    "speaker": "曉臻",
    "text": "老師有機物的種類好多喔",
    "is_pinned": false,
    "pin_level": 0,
    "commands": []
  },
  {
    "start": 221.18,
    "end": 224.16,
    "speaker": "曉臻",
    "text": "烴、醇、酸、酯",
    "is_pinned": false,
    "pin_level": 0,
    "commands": []
  },
  {
    "start": 224.36,
    "end": 226.91,
    "speaker": "曉臻",
    "text": "到底該怎麼分辨啊",
    "is_pinned": false,
    "pin_level": 0,
    "commands": []
  },
  {
    "start": 227.11,
    "end": 230.86,
    "speaker": "彥君",
    "text": "戰士們看黑板我們一個個來",
    "is_pinned": false,
    "pin_level": 0,
    "commands": []
  },
  {
    "start": 231.06,
    "end": 234.24,
    "speaker": "彥君",
    "text": "先看第一個烴類",
    "is_pinned": false,
    "pin_level": 0,
    "commands": []
  },
  {
    "start": 234.44,
    "end": 237.86,
    "speaker": "彥君",
    "text": "烴類裡面只有碳跟氫",
    "is_pinned": false,
    "pin_level": 0,
    "commands": []
  },
  {
    "start": 238.06,
    "end": 241.26,
    "speaker": "彥君",
    "text": "像是甲烷還有丙烷",
    "is_pinned": false,
    "pin_level": 0,
    "commands": []
  },
  {
    "start": 241.46,
    "end": 244.7,
    "speaker": "曉臻",
    "text": "講義說它們都不溶於水耶",
    "is_pinned": false,
    "pin_level": 0,
    "commands": []
  },
  {
    "start": 244.9,
    "end": 249.38,
    "speaker": "彥君",
    "text": "沒錯而且碳數越少",
    "is_pinned": false,
    "pin_level": 0,
    "commands": []
  },
  {
    "start": 249.58,
    "end": 252.73,
    "speaker": "彥君",
    "text": "它在常溫下是氣態的",
    "is_pinned": false,
    "pin_level": 0,
    "commands": []
  },
  {
    "start": 252.93,
    "end": 256.8,
    "speaker": "彥君",
    "text": "碳數越多就會變成液態跟固態",
    "is_pinned": false,
    "pin_level": 0,
    "commands": []
  },
  {
    "start": 257.0,
    "end": 333.26,
    "speaker": "彥君",
    "text": "烴類：只含碳氫、不溶於水、中性",
    "is_pinned": true,
    "pin_level": 1,
    "commands": [
      "釘選"
    ]
  },
  {
    "start": 265.27,
    "end": 267.58,
    "speaker": "曉臻",
    "text": "第二個是醇類",
    "is_pinned": false,
    "pin_level": 0,
    "commands": []
  },
  {
    "start": 267.78,
    "end": 270.82,
    "speaker": "曉臻",
    "text": "它有 $$OH$$ 原子團耶",
    "is_pinned": false,
    "pin_level": 0,
    "commands": [
      "$$OH$$"
    ]
  },
  {
    "start": 271.02,
    "end": 273.76,
    "speaker": "曉臻",
    "text": "那它是不是鹼性的啊",
    "is_pinned": false,
    "pin_level": 0,
    "commands": []
  },
  {
    "start": 273.96,
    "end": 277.71,
    "speaker": "彥君",
    "text": "戰士們這是超級大陷阱",
    "is_pinned": false,
    "pin_level": 0,
    "commands": []
  },
  {
    "start": 277.91,
    "end": 280.73,
    "speaker": "彥君",
    "text": "醇類的 $$OH$$",
    "is_pinned": false,
    "pin_level": 0,
    "commands": [
      "$$OH$$"
    ]
  },
  {
    "start": 280.93,
    "end": 285.88,
    "speaker": "彥君",
    "text": "在水裡不會解離所以是中性",
    "is_pinned": false,
    "pin_level": 0,
    "commands": []
  },
  {
    "start": 286.08,
    "end": 289.28,
    "speaker": "彥君",
    "text": "像是酒精就是醇類",
    "is_pinned": false,
    "pin_level": 0,
    "commands": []
  },
  {
    "start": 289.48,
    "end": 292.51,
    "speaker": "彥君",
    "text": "它可以完美溶於水",
    "is_pinned": false,
    "pin_level": 0,
    "commands": []
  },
  {
    "start": 292.71,
    "end": 295.41,
    "speaker": "曉臻",
    "text": "原來酒精是中性的",
    "is_pinned": false,
    "pin_level": 0,
    "commands": []
  },
  {
    "start": 295.61,
    "end": 333.26,
    "speaker": "彥君",
    "text": "醇類：含 OH 原子團、溶於水、中性",
    "is_pinned": true,
    "pin_level": 2,
    "commands": [
      "釘選"
    ]
  },
  {
    "start": 304.48,
    "end": 306.86,
    "speaker": "曉臻",
    "text": "那第三個酸類呢",
    "is_pinned": false,
    "pin_level": 0,
    "commands": []
  },
  {
    "start": 307.06,
    "end": 310.84,
    "speaker": "彥君",
    "text": "酸類有 $COOH$",
    "is_pinned": false,
    "pin_level": 0,
    "commands": [
      "$COOH$"
    ]
  },
  {
    "start": 311.04,
    "end": 313.83,
    "speaker": "彥君",
    "text": "像是常見的醋酸",
    "is_pinned": false,
    "pin_level": 0,
    "commands": []
  },
  {
    "start": 314.03,
    "end": 316.99,
    "speaker": "彥君",
    "text": "溶於水就是酸性",
    "is_pinned": false,
    "pin_level": 0,
    "commands": []
  },
  {
    "start": 317.19,
    "end": 333.26,
    "speaker": "彥君",
    "text": "酸類：含 COOH、溶於水、酸性",
    "is_pinned": true,
    "pin_level": 3,
    "commands": [
      "釘選"
    ]
  },
  {
    "start": 325.54,
    "end": 330.06,
    "speaker": "彥君",
    "text": "給你們三秒鐘把這三個的基本盤記熟",
    "is_pinned": false,
    "pin_level": 0,
    "commands": []
  },
  {
    "start": 333.26,
    "end": 336.1,
    "speaker": "曉臻",
    "text": "最後要進入大魔王了",
    "is_pinned": false,
    "pin_level": 0,
    "commands": []
  },
  {
    "start": 336.3,
    "end": 338.75,
    "speaker": "曉臻",
    "text": "右邊的酯化反應",
    "is_pinned": false,
    "pin_level": 0,
    "commands": []
  },
  {
    "start": 338.95,
    "end": 342.49,
    "speaker": "彥君",
    "text": "戰士們這是必考五顆星",
    "is_pinned": false,
    "pin_level": 0,
    "commands": []
  },
  {
    "start": 342.69,
    "end": 345.7,
    "speaker": "彥君",
    "text": "有機酸加上醇類",
    "is_pinned": false,
    "pin_level": 0,
    "commands": []
  },
  {
    "start": 345.9,
    "end": 349.0,
    "speaker": "彥君",
    "text": "會變成酯類加上水",
    "is_pinned": false,
    "pin_level": 0,
    "commands": []
  },
  {
    "start": 349.2,
    "end": 439.98,
    "speaker": "彥君",
    "text": "有機酸 $+$ 醇 $\\rightarrow$ 酯 $+$ 水",
    "is_pinned": true,
    "pin_level": 1,
    "commands": [
      "釘選",
      "有機酸 $+$ 醇 $\\rightarrow$ 酯 $+$ 水"
    ]
  },
  {
    "start": 353.32,
    "end": 357.02,
    "speaker": "曉臻",
    "text": "老師箭頭上面寫著硫酸耶",
    "is_pinned": false,
    "pin_level": 0,
    "commands": []
  },
  {
    "start": 357.22,
    "end": 360.26,
    "speaker": "彥君",
    "text": "這裡必須使用濃硫酸",
    "is_pinned": false,
    "pin_level": 0,
    "commands": []
  },
  {
    "start": 360.46,
    "end": 363.18,
    "speaker": "曉臻",
    "text": "為什麼一定要濃硫酸",
    "is_pinned": false,
    "pin_level": 0,
    "commands": []
  },
  {
    "start": 363.38,
    "end": 367.08,
    "speaker": "彥君",
    "text": "因為濃硫酸有強烈的脫水性",
    "is_pinned": false,
    "pin_level": 0,
    "commands": []
  },
  {
    "start": 367.28,
    "end": 370.77,
    "speaker": "彥君",
    "text": "它可以把產物裡面的水吸走",
    "is_pinned": false,
    "pin_level": 0,
    "commands": []
  },
  {
    "start": 370.97,
    "end": 374.26,
    "speaker": "彥君",
    "text": "讓反應一直往右邊進行",
    "is_pinned": false,
    "pin_level": 0,
    "commands": []
  },
  {
    "start": 374.46,
    "end": 378.24,
    "speaker": "彥君",
    "text": "它同時扮演催化劑跟脫水劑",
    "is_pinned": false,
    "pin_level": 0,
    "commands": []
  },
  {
    "start": 378.44,
    "end": 382.17,
    "speaker": "曉臻",
    "text": "哇原來是雙重角色",
    "is_pinned": false,
    "pin_level": 0,
    "commands": []
  },
  {
    "start": 382.37,
    "end": 385.06,
    "speaker": "曉臻",
    "text": "那產生出來的酯類",
    "is_pinned": false,
    "pin_level": 0,
    "commands": []
  },
  {
    "start": 385.26,
    "end": 387.82,
    "speaker": "曉臻",
    "text": "到底有什麼特性啊",
    "is_pinned": false,
    "pin_level": 0,
    "commands": []
  },
  {
    "start": 388.02,
    "end": 390.71,
    "speaker": "彥君",
    "text": "記住三個關鍵",
    "is_pinned": false,
    "pin_level": 0,
    "commands": []
  },
  {
    "start": 390.91,
    "end": 394.14,
    "speaker": "彥君",
    "text": "第一個它不溶於水",
    "is_pinned": false,
    "pin_level": 0,
    "commands": []
  },
  {
    "start": 394.34,
    "end": 397.61,
    "speaker": "曉臻",
    "text": "講義上寫它會浮在水面上",
    "is_pinned": false,
    "pin_level": 0,
    "commands": []
  },
  {
    "start": 397.81,
    "end": 401.32,
    "speaker": "彥君",
    "text": "這代表它的密度比水還要小",
    "is_pinned": false,
    "pin_level": 0,
    "commands": []
  },
  {
    "start": 401.52,
    "end": 404.55,
    "speaker": "曉臻",
    "text": "還有特殊的香味對不對",
    "is_pinned": false,
    "pin_level": 0,
    "commands": []
  },
  {
    "start": 404.75,
    "end": 409.75,
    "speaker": "彥君",
    "text": "沒錯像是各種水果的香味",
    "is_pinned": false,
    "pin_level": 0,
    "commands": []
  },
  {
    "start": 409.95,
    "end": 413.2,
    "speaker": "彥君",
    "text": "香蕉油、蘋果油",
    "is_pinned": false,
    "pin_level": 0,
    "commands": []
  },
  {
    "start": 413.4,
    "end": 416.34,
    "speaker": "彥君",
    "text": "它們通通都是酯類喔",
    "is_pinned": false,
    "pin_level": 0,
    "commands": []
  },
  {
    "start": 416.54,
    "end": 439.98,
    "speaker": "彥君",
    "text": "酯類：不溶於水、密度小、有香味",
    "is_pinned": true,
    "pin_level": 2,
    "commands": [
      "釘選"
    ]
  },
  {
    "start": 425.07,
    "end": 428.78,
    "speaker": "曉臻",
    "text": "哇龐大的有機化學",
    "is_pinned": false,
    "pin_level": 0,
    "commands": []
  },
  {
    "start": 428.98,
    "end": 431.96,
    "speaker": "曉臻",
    "text": "這樣拆解變得超級清楚",
    "is_pinned": false,
    "pin_level": 0,
    "commands": []
  },
  {
    "start": 432.16,
    "end": 436.78,
    "speaker": "彥君",
    "text": "給你們三秒鐘把酯類的特性印在腦海裡",
    "is_pinned": false,
    "pin_level": 0,
    "commands": []
  },
  {
    "start": 439.98,
    "end": 443.85,
    "speaker": "彥君",
    "text": "觀念一旦通透考題直接秒殺",
    "is_pinned": false,
    "pin_level": 0,
    "commands": []
  },
  {
    "start": 444.05,
    "end": 446.65,
    "speaker": "彥君",
    "text": "我是彥君老師",
    "is_pinned": false,
    "pin_level": 0,
    "commands": []
  },
  {
    "start": 446.85,
    "end": 449.18,
    "speaker": "曉臻",
    "text": "我是曉臻助教",
    "is_pinned": false,
    "pin_level": 0,
    "commands": []
  },
  {
    "start": 449.38,
    "end": 452.87,
    "speaker": "合聲",
    "text": "有機必碳酸醇生酯",
    "is_pinned": false,
    "pin_level": 0,
    "commands": []
  },
  {
    "start": 453.07,
    "end": 456.61,
    "speaker": "合聲",
    "text": "戰士們我們頂峰相見",
    "is_pinned": false,
    "pin_level": 0,
    "commands": []
  }
]